src/__init__.py
src/cnncls.py
src/utilbase.py
imutilbox-0.0.1.dist-info/METADATA
imutilbox-0.0.1.dist-info/WHEEL
imutilbox-0.0.1.dist-info/top_level.txt
imutilbox-0.0.1.dist-info/zip-safe
imutilbox-0.0.1.dist-info/RECORD
